mysql_connect/__init__.py
mysql_connect/mysql_crud.py
mysql_crud_automation-0.0.11.dist-info/LICENSE
mysql_crud_automation-0.0.11.dist-info/METADATA
mysql_crud_automation-0.0.11.dist-info/WHEEL
mysql_crud_automation-0.0.11.dist-info/top_level.txt
mysql_crud_automation-0.0.11.dist-info/RECORD
