Metadata-Version: 2.1
Name: mysql_crud_automation
Version: 0.0.11
Summary: A python package for connecting with database.
Home-page: https://github.com/Minali0/mysqlconnectorpkg
Author: Minali0
Author-email: minali.jain@seaflux.tech
License: MIT
Project-URL: Bug Tracker, https://github.com/Minali0/mysqlconnectorpkg/issues
Classifier: Programming Language :: Python :: 3.11
Classifier: Operating System :: OS Independent
License-File: LICENSE
Requires-Dist: mysql-connector-python
Requires-Dist: dnspython
Requires-Dist: pandas
Requires-Dist: numpy
Requires-Dist: ensure
Requires-Dist: tox
Provides-Extra: testing
Requires-Dist: pytest==7.4.2; extra == "testing"
Requires-Dist: black==23.1.0; extra == "testing"
Requires-Dist: flake8==6.1.0; extra == "testing"
Requires-Dist: mypy==1.2.0; extra == "testing"
